python_gameoflife/main.py
python_gameoflife-1.0.0.dist-info/METADATA
python_gameoflife-1.0.0.dist-info/WHEEL
python_gameoflife-1.0.0.dist-info/entry_points.txt
python_gameoflife-1.0.0.dist-info/top_level.txt
python_gameoflife-1.0.0.dist-info/RECORD
